Metadata-Version: 2.1
Name: pyddi
Version: 0.0.4
Summary: Identifies Sources that Require Direction-Dependent Calibration.
Home-page: https://github.com/Sebokolodi/pyddi
Author: Lerato Sebokolodi
Author-email: mll.sebokolodi@gmail.com
License: GNU GPL v3
Platform: UNKNOWN
Classifier: Intended Audience :: Developers
Classifier: Topic :: Scientific/Engineering :: Astronomy
Classifier: Topic :: Software Development :: Libraries :: Python Modules
